setup.py
zach/__init__.py
zach.egg-info/PKG-INFO
zach.egg-info/SOURCES.txt
zach.egg-info/dependency_links.txt
zach.egg-info/top_level.txt