Metadata-Version: 1.0
Name: zach
Version: 1.0
Summary: See what Zach's been up to.
Home-page: http://github.com/zachwill/import_zach
Author: Zach Williams
Author-email: hey@zachwill.com
License: Public Domain
Keywords: zach,zachwill,zach will,useless
Platform: UNKNOWN
Classifier: Intended Audience :: Developers
Classifier: Natural Language :: English
Classifier: License :: OSI Approved :: MIT License
Classifier: Programming Language :: Python
Classifier: Programming Language :: Python :: 2.6
Classifier: Programming Language :: Python :: 2.7
